LICENSE
README.md
setup.py
beets_userrating.egg-info/PKG-INFO
beets_userrating.egg-info/SOURCES.txt
beets_userrating.egg-info/dependency_links.txt
beets_userrating.egg-info/requires.txt
beets_userrating.egg-info/top_level.txt
beetsplug/__init__.py
beetsplug/banshee.py
beetsplug/mm.py
beetsplug/scaler.py
beetsplug/userrating.py
beetsplug/wmp.py
test/test_banshee_scaler.py
test/test_mm_scaler.py
test/test_userrating.py
test/test_userrating_import.py
test/test_wmp_scaler.py